{
  "AT": { "name": "Austria", "name_local": "Österreich", "population": 9100000, "gdp_eur": 447000000000, "eea": true },
  "BE": { "name": "Belgium", "name_local": "België", "population": 11700000, "gdp_eur": 554000000000, "eea": true },
  "BG": { "name": "Bulgaria", "name_local": "България", "population": 6500000, "gdp_eur": 95000000000, "eea": true },
  "HR": { "name": "Croatia", "name_local": "Hrvatska", "population": 3900000, "gdp_eur": 68000000000, "eea": true },
  "CY": { "name": "Cyprus", "name_local": "Κύπρος", "population": 920000, "gdp_eur": 28000000000, "eea": true },
  "CZ": { "name": "Czech Republic", "name_local": "Česko", "population": 10900000, "gdp_eur": 290000000000, "eea": true },
  "DK": { "name": "Denmark", "name_local": "Danmark", "population": 5900000, "gdp_eur": 380000000000, "eea": true },
  "EE": { "name": "Estonia", "name_local": "Eesti", "population": 1400000, "gdp_eur": 38000000000, "eea": true },
  "FI": { "name": "Finland", "name_local": "Suomi", "population": 5600000, "gdp_eur": 275000000000, "eea": true },
  "FR": { "name": "France", "name_local": "France", "population": 68000000, "gdp_eur": 2800000000000, "eea": true },
  "DE": { "name": "Germany", "name_local": "Deutschland", "population": 84000000, "gdp_eur": 4100000000000, "eea": true },
  "GR": { "name": "Greece", "name_local": "Ελλάδα", "population": 10400000, "gdp_eur": 220000000000, "eea": true },
  "HU": { "name": "Hungary", "name_local": "Magyarország", "population": 9700000, "gdp_eur": 180000000000, "eea": true },
  "IS": { "name": "Iceland", "name_local": "Ísland", "population": 380000, "gdp_eur": 25000000000, "eea": true },
  "IE": { "name": "Ireland", "name_local": "Éire", "population": 5200000, "gdp_eur": 500000000000, "eea": true },
  "IT": { "name": "Italy", "name_local": "Italia", "population": 59000000, "gdp_eur": 2000000000000, "eea": true },
  "LV": { "name": "Latvia", "name_local": "Latvija", "population": 1900000, "gdp_eur": 40000000000, "eea": true },
  "LI": { "name": "Liechtenstein", "name_local": "Liechtenstein", "population": 40000, "gdp_eur": 7000000000, "eea": true },
  "LT": { "name": "Lithuania", "name_local": "Lietuva", "population": 2900000, "gdp_eur": 67000000000, "eea": true },
  "LU": { "name": "Luxembourg", "name_local": "Luxembourg", "population": 660000, "gdp_eur": 80000000000, "eea": true },
  "MT": { "name": "Malta", "name_local": "Malta", "population": 540000, "gdp_eur": 18000000000, "eea": true },
  "NL": { "name": "Netherlands", "name_local": "Nederland", "population": 17800000, "gdp_eur": 1010000000000, "eea": true },
  "NO": { "name": "Norway", "name_local": "Norge", "population": 5500000, "gdp_eur": 480000000000, "eea": true },
  "PL": { "name": "Poland", "name_local": "Polska", "population": 37600000, "gdp_eur": 680000000000, "eea": true },
  "PT": { "name": "Portugal", "name_local": "Portugal", "population": 10400000, "gdp_eur": 260000000000, "eea": true },
  "RO": { "name": "Romania", "name_local": "România", "population": 19000000, "gdp_eur": 300000000000, "eea": true },
  "SK": { "name": "Slovakia", "name_local": "Slovensko", "population": 5400000, "gdp_eur": 115000000000, "eea": true },
  "SI": { "name": "Slovenia", "name_local": "Slovenija", "population": 2100000, "gdp_eur": 62000000000, "eea": true },
  "ES": { "name": "Spain", "name_local": "España", "population": 48000000, "gdp_eur": 1400000000000, "eea": true },
  "SE": { "name": "Sweden", "name_local": "Sverige", "population": 10500000, "gdp_eur": 560000000000, "eea": true },
  "CH": { "name": "Switzerland", "name_local": "Schweiz", "population": 8800000, "gdp_eur": 750000000000, "eea": false }
}
